PyMathSolver/Quadratic.py
PyMathSolver/__init__.py
PyMathSolver-1.0.3.dist-info/LICENSE.txt
PyMathSolver-1.0.3.dist-info/METADATA
PyMathSolver-1.0.3.dist-info/WHEEL
PyMathSolver-1.0.3.dist-info/top_level.txt
PyMathSolver-1.0.3.dist-info/RECORD
