Metadata-Version: 2.1
Name: PyMathSolver
Version: 1.0.3
Summary: Python module to solve math problems and work on calculations.
Home-page: https://github.com/Anikethc/PyMathSolver
Download-URL: https://pypi.org/project/pymathsolver
Author: Aniketh Chavare
Author-email: anikethchavare@outlook.com
License: MIT
Keywords: Math,Calculations
License-File: LICENSE.txt
Requires-Dist: termcolor
